machfs/__init__.py
machfs/bitmanip.py
machfs/btree.py
machfs/directory.py
machfs/main.py
machfs-1.3.data/scripts/DumpHFS
machfs-1.3.data/scripts/MakeHFS
machfs-1.3.dist-info/LICENSE
machfs-1.3.dist-info/METADATA
machfs-1.3.dist-info/WHEEL
machfs-1.3.dist-info/top_level.txt
machfs-1.3.dist-info/RECORD
