Metadata-Version: 2.1
Name: machfs
Version: 1.3
Summary: Library for reading and writing Macintosh HFS volumes
Home-page: https://github.com/elliotnunn/machfs
Author: Elliot Nunn
Author-email: elliotnunn@me.com
License: MIT
Platform: UNKNOWN
Classifier: Programming Language :: Python :: 3 :: Only
Classifier: Operating System :: OS Independent
Classifier: License :: OSI Approved :: MIT License
Classifier: Topic :: System :: Filesystems
